uservice/__init__.py
uservice/__main__.py
uservice/consumer.py
uservice/contexts.py
uservice/dependencies.py
uservice/entrypoints.py
uservice/importer.py
uservice/main.py
uservice/runner.py
uservice/service.py
uservice/settings.py
uservice/test.py
uservice/utils.py
uservice/amqp/consumer.py
uservice/amqp/events.py
uservice/amqp/rpc.py
uservice/cli/__init__.py
uservice/cli/run.py
uservice/cli/schema.py
uservice/redis/events.py
uservice/supervisors/__init__.py
uservice/supervisors/change_reload.py
uservice/supervisors/multiprocess.py
uservice/supervisors/subprocess.py
uservice-0.1.2.dist-info/METADATA
uservice-0.1.2.dist-info/WHEEL
uservice-0.1.2.dist-info/entry_points.txt
uservice-0.1.2.dist-info/RECORD
