Metadata-Version: 2.1
Name: uservice
Version: 0.1.2
Summary: A async microservice framework for python
Project-URL: Homepage, https://github.com/dahlkar/uservice
Author-email: Johan Dahlkar <johan.dahlkar@gmail.com>
License-Expression: MIT
Requires-Python: >=3.10
Requires-Dist: aio-pika>=9.0.7
Requires-Dist: click>=8.1.3
Requires-Dist: pydantic>=1.10.8
Requires-Dist: pyyaml>=6.0
Requires-Dist: uvloop>=0.17.0
Requires-Dist: watchfiles>=0.19.0
Provides-Extra: test
Requires-Dist: docker==6.1.3; extra == 'test'
Requires-Dist: pytest-asyncio==0.21.0; extra == 'test'
Requires-Dist: pytest==7.3.1; extra == 'test'
